qran/__init__.py
qran/__main__.py
qran/models.py
qran/mushaf.py
qran/mushaf_simple.json
qran/mushaf_uthmani.json
qran/update_data.py
qran/util.py
qran-1.0.1.dist-info/licenses/LICENSE
qran-1.0.1.dist-info/METADATA
qran-1.0.1.dist-info/WHEEL
qran-1.0.1.dist-info/entry_points.txt
qran-1.0.1.dist-info/top_level.txt
qran-1.0.1.dist-info/RECORD
