Metadata-Version: 2.4
Name: qran
Version: 1.0.1
Summary: Quran text API
Author-email: Alicia Gonzalez Martinez <aliciagm85+github@gmail.com>
Maintainer-email: Alicia Gonzalez Martinez <aliciagm85+github@gmail.com>
License-Expression: MIT
Project-URL: Homepage, https://qran-app.onrender.com/
Project-URL: Repository, https://github.com/kabikaj/qran.git
Project-URL: Issues, https://github.com/kabikaj/qran/issues
Project-URL: Changelog, https://github.com/kabikaj/qran/blob/master/CHANGELOG.md
Keywords: quran,nlp,grapheme,archigrapheme,kabikaj
Classifier: Development Status :: 4 - Beta
Classifier: Programming Language :: Python :: 3.9
Classifier: Programming Language :: Python :: 3.10
Classifier: Programming Language :: Python :: 3.11
Classifier: Programming Language :: Python :: 3.12
Classifier: Programming Language :: Python :: 3.13
Requires-Python: >=3.9
License-File: LICENSE
Requires-Dist: orjson
Requires-Dist: pydantic
Provides-Extra: dev
Requires-Dist: pytest>=8.3.5; extra == "dev"
Requires-Dist: ruff>=0.11.0; extra == "dev"
Requires-Dist: vermin>=1.6.0; extra == "dev"
Requires-Dist: mypy>=1.16.1; extra == "dev"
Dynamic: license-file
